pserver.mailer-1.0.1.dev0-py3.5-nspkg.pth
pserver/mailer/__init__.py
pserver/mailer/api.py
pserver/mailer/configure.zcml
pserver/mailer/exceptions.py
pserver/mailer/interfaces.py
pserver/mailer/utility.py
pserver.mailer-1.0.1.dev0.dist-info/DESCRIPTION.rst
pserver.mailer-1.0.1.dev0.dist-info/METADATA
pserver.mailer-1.0.1.dev0.dist-info/RECORD
pserver.mailer-1.0.1.dev0.dist-info/WHEEL
pserver.mailer-1.0.1.dev0.dist-info/entry_points.txt
pserver.mailer-1.0.1.dev0.dist-info/metadata.json
pserver.mailer-1.0.1.dev0.dist-info/namespace_packages.txt
pserver.mailer-1.0.1.dev0.dist-info/top_level.txt
pserver.mailer-1.0.1.dev0.dist-info/zip-safe
