Metadata-Version: 2.0
Name: pserver.mailer
Version: 1.0.1.dev0
Summary: UNKNOWN
Home-page: https://github.com/pyrenees/pserver.mailer
Author: Nathan Van Gheem
Author-email: nathan.vangheem@wildcardcorp.com
License: BSD
Keywords: async mail plone
Platform: UNKNOWN
Classifier: Programming Language :: Python :: 3.5
Classifier: Programming Language :: Python :: 3.6
Classifier: Topic :: Software Development :: Libraries :: Python Modules
Requires-Dist: setuptools
Requires-Dist: plone.server
Requires-Dist: repoze.sendmail (>=4.1)
Requires-Dist: transaction
Requires-Dist: html2text
Requires-Dist: aiosmtplib
